testing_tasks_mock/__FRACTAL_MANIFEST__.json
testing_tasks_mock/__init__.py
testing_tasks_mock/generic_task.py
testing_tasks_mock/generic_task_parallel.py
testing_tasks_mock-0.1.3.dist-info/licenses/LICENSE
testing_tasks_mock-0.1.3.dist-info/METADATA
testing_tasks_mock-0.1.3.dist-info/WHEEL
testing_tasks_mock-0.1.3.dist-info/top_level.txt
testing_tasks_mock-0.1.3.dist-info/RECORD
